{
  "parent": "minecraft:recipes/root",
  "criteria": {
    "has_duck": {
      "trigger": "minecraft:inventory_changed",
      "conditions": {
        "items": [
          {
            "items": [
              "naturalist:duck"
            ]
          }
        ]
      }
    },
    "has_the_recipe": {
      "conditions": {
        "recipe": "naturalist:cooked_duck"
      },
      "trigger": "minecraft:recipe_unlocked"
    }
  },
  "requirements": [
    [
      "has_duck",
      "has_the_recipe"
    ]
  ],
  "rewards": {
    "recipes": [
      "naturalist:cooked_duck",
      "naturalist:cooked_duck_from_smoking",
      "naturalist:cooked_duck_from_campfire_cooking"
    ]
  }
}